Metadata-Version: 2.1
Name: random-xe
Version: 1.0.0
Summary: Random number generator with eXtra Entropy
Home-page: https://github.com/amaslyaev/random_xe_py
Author: Alexander Maslyaev
Author-email: maslyaev@gmail.com
License: UNKNOWN
Project-URL: Bug Reports, https://github.com/amaslyaev/random_xe_py/issues
Project-URL: Source, https://github.com/amaslyaev/random_xe_py
Keywords: random rng prng
Platform: UNKNOWN
Classifier: Development Status :: 5 - Production/Stable
Classifier: Intended Audience :: Developers
Classifier: Intended Audience :: Education
Classifier: Intended Audience :: Science/Research
Classifier: Topic :: Security :: Cryptography
Classifier: Topic :: Software Development :: Libraries
Classifier: License :: CC0 1.0 Universal (CC0 1.0) Public Domain Dedication
Classifier: Programming Language :: Python :: 3
Classifier: Programming Language :: Python :: 3.4
Classifier: Programming Language :: Python :: 3.5
Classifier: Programming Language :: Python :: 3.6
Classifier: Programming Language :: Python :: 3.7
